pipe_tool/__init__.py
pipe_tool-0.0.5.dist-info/DESCRIPTION.rst
pipe_tool-0.0.5.dist-info/METADATA
pipe_tool-0.0.5.dist-info/RECORD
pipe_tool-0.0.5.dist-info/WHEEL
pipe_tool-0.0.5.dist-info/entry_points.txt
pipe_tool-0.0.5.dist-info/metadata.json
pipe_tool-0.0.5.dist-info/top_level.txt
